MANIFEST.in
README.txt
plonetheme.nautica05-configure.zcml
setup.cfg
setup.py
docs/HISTORY.txt
docs/INSTALL.txt
docs/LICENSE.GPL
docs/LICENSE.txt
plonetheme/.DS_Store
plonetheme/__init__.py
plonetheme.nautica05.egg-info/PKG-INFO
plonetheme.nautica05.egg-info/SOURCES.txt
plonetheme.nautica05.egg-info/dependency_links.txt
plonetheme.nautica05.egg-info/entry_points.txt
plonetheme.nautica05.egg-info/namespace_packages.txt
plonetheme.nautica05.egg-info/not-zip-safe
plonetheme.nautica05.egg-info/requires.txt
plonetheme.nautica05.egg-info/top_level.txt
plonetheme/nautica05/.DS_Store
plonetheme/nautica05/__init__.py
plonetheme/nautica05/configure.zcml
plonetheme/nautica05/profiles.zcml
plonetheme/nautica05/screenshot.png
plonetheme/nautica05/setuphandlers.py
plonetheme/nautica05/skins.zcml
plonetheme/nautica05/tests.py
plonetheme/nautica05/version.txt
plonetheme/nautica05/browser/.DS_Store
plonetheme/nautica05/browser/__init__.py
plonetheme/nautica05/browser/configure.zcml
plonetheme/nautica05/browser/interfaces.py
plonetheme/nautica05/browser/viewlet.pt
plonetheme/nautica05/browser/viewlets.py
plonetheme/nautica05/browser/images/README.txt
plonetheme/nautica05/browser/stylesheets/README.txt
plonetheme/nautica05/browser/stylesheets/main.css
plonetheme/nautica05/profiles/.DS_Store
plonetheme/nautica05/profiles/default/cssregistry.xml
plonetheme/nautica05/profiles/default/import_steps.xml
plonetheme/nautica05/profiles/default/jsregistry.xml
plonetheme/nautica05/profiles/default/metadata.xml
plonetheme/nautica05/profiles/default/plonetheme.nautica05_various.txt
plonetheme/nautica05/profiles/default/skins.xml
plonetheme/nautica05/profiles/default/viewlets.xml
plonetheme/nautica05/skins/.DS_Store
plonetheme/nautica05/skins/plonetheme_nautica05_custom_images/.DS_Store
plonetheme/nautica05/skins/plonetheme_nautica05_custom_images/01.jpg
plonetheme/nautica05/skins/plonetheme_nautica05_custom_images/02.jpg
plonetheme/nautica05/skins/plonetheme_nautica05_custom_images/03.jpg
plonetheme/nautica05/skins/plonetheme_nautica05_custom_images/04.jpg
plonetheme/nautica05/skins/plonetheme_nautica05_custom_images/05.jpg
plonetheme/nautica05/skins/plonetheme_nautica05_custom_images/CONTENT.txt
plonetheme/nautica05/skins/plonetheme_nautica05_custom_images/blank.gif
plonetheme/nautica05/skins/plonetheme_nautica05_custom_images/firefox.jpg
