Metadata-Version: 1.0
Name: plonetheme.nautica05
Version: 0.2
Summary: An installable theme for Plone 3.x
Home-page: http://svn.plone.org/svn/collective/
Author: WebLion group at Penn State University
Author-email: support@weblion.psu.edu
License: GPL
Keywords: web zope plone theme
Platform: UNKNOWN
Classifier: Framework :: Plone
Classifier: Programming Language :: Python
Classifier: Topic :: Software Development :: Libraries :: Python Modules
